gguf_modeldb/__init__.py
gguf_modeldb/db.py
gguf_modeldb/db_settings.py
gguf_modeldb/model_data.py
gguf_modeldb/gguf_models/dolphin-2_6-phi-2.Q2_K.json
gguf_modeldb/gguf_models/dolphin-2_6-phi-2.Q3_K_L.json
gguf_modeldb/gguf_models/dolphin-2_6-phi-2.Q3_K_M.json
gguf_modeldb/gguf_models/dolphin-2_6-phi-2.Q3_K_S.json
gguf_modeldb/gguf_models/dolphin-2_6-phi-2.Q4_0.json
gguf_modeldb/gguf_models/dolphin-2_6-phi-2.Q4_K_M.json
gguf_modeldb/gguf_models/dolphin-2_6-phi-2.Q4_K_S.json
gguf_modeldb/gguf_models/dolphin-2_6-phi-2.Q5_0.json
gguf_modeldb/gguf_models/dolphin-2_6-phi-2.Q5_K_M.json
gguf_modeldb/gguf_models/dolphin-2_6-phi-2.Q5_K_S.json
gguf_modeldb/gguf_models/dolphin-2_6-phi-2.Q6_K.json
gguf_modeldb/gguf_models/dolphin-2_6-phi-2.Q8_0.json
gguf_modeldb/gguf_models/llama-pro-8b-instruct.Q2_K.json
gguf_modeldb/gguf_models/llama-pro-8b-instruct.Q3_K_L.json
gguf_modeldb/gguf_models/llama-pro-8b-instruct.Q3_K_M.json
gguf_modeldb/gguf_models/llama-pro-8b-instruct.Q3_K_S.json
gguf_modeldb/gguf_models/llama-pro-8b-instruct.Q4_0.json
gguf_modeldb/gguf_models/llama-pro-8b-instruct.Q4_K_M.json
gguf_modeldb/gguf_models/llama-pro-8b-instruct.Q4_K_S.json
gguf_modeldb/gguf_models/llama-pro-8b-instruct.Q5_0.json
gguf_modeldb/gguf_models/llama-pro-8b-instruct.Q5_K_M.json
gguf_modeldb/gguf_models/llama-pro-8b-instruct.Q5_K_S.json
gguf_modeldb/gguf_models/llama-pro-8b-instruct.Q6_K.json
gguf_modeldb/gguf_models/llama-pro-8b-instruct.Q8_0.json
gguf_modeldb/gguf_models/mistral-7b-instruct-v0.2.Q2_K.json
gguf_modeldb/gguf_models/mistral-7b-instruct-v0.2.Q3_K_L.json
gguf_modeldb/gguf_models/mistral-7b-instruct-v0.2.Q3_K_M.json
gguf_modeldb/gguf_models/mistral-7b-instruct-v0.2.Q3_K_S.json
gguf_modeldb/gguf_models/mistral-7b-instruct-v0.2.Q4_0.json
gguf_modeldb/gguf_models/mistral-7b-instruct-v0.2.Q4_K_M.json
gguf_modeldb/gguf_models/mistral-7b-instruct-v0.2.Q4_K_S.json
gguf_modeldb/gguf_models/mistral-7b-instruct-v0.2.Q5_0.json
gguf_modeldb/gguf_models/mistral-7b-instruct-v0.2.Q5_K_M.json
gguf_modeldb-0.0.3.dist-info/METADATA
gguf_modeldb-0.0.3.dist-info/WHEEL
gguf_modeldb-0.0.3.dist-info/top_level.txt
gguf_modeldb-0.0.3.dist-info/RECORD
